Metadata-Version: 2.1
Name: hf_down
Version: 1.0.3
Summary: A tool to download files from Hugging Face repositories.
Home-page: 
Author: LEL
Author-email: 2324171649@qq.com
Requires-Python: >=3.6
License-File: LICENSE
